{
    "清体力_战略行动": {
        "recognition": {
            "param": {
                "expected": [
                    "戰略行動"
                ]
            }
        }
    },
    "清体力_关卡选择": {
        "recognition": {
            "param": {
                "expected": [
                    "象徵車廂"
                ]
            }
        }
    },
    "清体力_象征车厢": {
        "recognition": {
            "param": {
                "expected": [
                    "象徵車廂"
                ]
            }
        }
    },
    "清体力_经验本": {
        "recognition": {
            "param": {
                "expected": [
                    "前往"
                ]
            }
        }
    },
    "清体力_准备战斗": {
        "recognition": {
            "param": {
                "expected": [
                    "開始挑戰"
                ]
            }
        }
    },
    "清体力_4X": {
        "recognition": {
            "param": {
                "expected": [
                    "x4",
                    "×4",
                    "X4"
                ]
            }
        }
    },
    "清体力_开始挑战4": {
        "recognition": {
            "param": {
                "expected": [
                    "開始挑戰"
                ]
            }
        }
    },
    "清体力_没的吃了": {
        "recognition": {
            "param": {
                "expected": [
                    "是否消耗40個超相塵"
                ]
            }
        }
    },
    "清体力_判断合剂余量": {
        "recognition": {
            "param": {
                "expected": [
                    "是否消耗1個"
                ]
            }
        }
    },
    "清体力_4x行动前检测1": {
        "recognition": {
            "param": {
                "expected": [
                    "行動開始"
                ]
            }
        }
    },
    "清体力_4x行动前检测2": {
        "recognition": {
            "param": {
                "expected": [
                    "行動開始"
                ]
            }
        }
    },
    "清体力_使用稳定合剂": {
        "recognition": {
            "param": {
                "expected": [
                    "確定"
                ]
            }
        }
    },
    "清体力_4X行动": {
        "recognition": {
            "param": {
                "expected": [
                    "行動開始"
                ]
            }
        }
    },
    "清体力_3X": {
        "recognition": {
            "param": {
                "expected": [
                    "x3",
                    "×3"
                ]
            }
        }
    },
    "清体力_4X升级": {
        "recognition": {
            "param": {
                "expected": [
                    "點擊空白處關閉"
                ]
            }
        }
    },
    "清体力_结束行动并检查": {
        "recognition": {
            "param": {
                "expected": [
                    "確定"
                ]
            }
        }
    },
    "清体力_确定4X战斗": {
        "recognition": {
            "param": {
                "expected": [
                    "行動開始"
                ]
            }
        }
    },
    "清体力_等待指令": {
        "recognition": {
            "param": {
                "expected": [
                    "瞬時調度"
                ]
            }
        }
    },
    "清体力_开始挑战3": {
        "recognition": {
            "param": {
                "expected": [
                    "開始挑戰"
                ]
            }
        }
    },
    "清体力_关闭合剂界面": {
        "recognition": {
            "param": {
                "expected": [
                    "取消"
                ]
            }
        }
    },
    "清体力_3X及以下行动前检测1": {
        "recognition": {
            "param": {
                "expected": [
                    "行動開始"
                ]
            }
        }
    },
    "清体力_3X及以下行动前检测2": {
        "recognition": {
            "param": {
                "expected": [
                    "行動開始"
                ]
            }
        }
    },
    "清体力_2X": {
        "recognition": {
            "param": {
                "expected": [
                    "x2",
                    "×2"
                ]
            }
        }
    },
    "清体力_3X及以下行动": {
        "recognition": {
            "param": {
                "expected": [
                    "行動開始"
                ]
            }
        }
    },
    "清体力_开始挑战2": {
        "recognition": {
            "param": {
                "expected": [
                    "開始挑戰"
                ]
            }
        }
    },
    "清体力_3X及以下升级": {
        "recognition": {
            "param": {
                "expected": [
                    "點擊空白處關閉"
                ]
            }
        }
    },
    "清体力_行动结束": {
        "recognition": {
            "param": {
                "expected": [
                    "確定"
                ]
            }
        }
    },
    "清体力_确定3X及以下战斗": {
        "recognition": {
            "param": {
                "expected": [
                    "行動開始"
                ]
            }
        }
    },
    "清体力_再动": {
        "recognition": {
            "param": {
                "expected": [
                    "確定"
                ]
            }
        }
    },
    "清体力_1X": {
        "recognition": {
            "param": {
                "expected": [
                    "x1",
                    "×1"
                ]
            }
        }
    },
    "清体力_开始挑战1": {
        "recognition": {
            "param": {
                "expected": [
                    "開始挑戰"
                ]
            }
        }
    },
    "清体力_设置助战": {
        "recognition": {
            "param": {
                "expected": [
                    "設置助戰"
                ]
            }
        }
    },
    "清体力_检查剩余助战次数": {
        "recognition": {
            "param": {
                "expected": [
                    "今日助戰次數已不足"
                ]
            }
        }
    },
    "清体力_已存在相同特工": {
        "recognition": {
            "param": {
                "expected": [
                    "已存在相同特工"
                ]
            }
        }
    },
    "清体力_取消下阵": {
        "recognition": {
            "param": {
                "expected": [
                    "取消"
                ]
            }
        }
    },
    "清体力_刷新助战": {
        "recognition": {
            "param": {
                "expected": [
                    "刷新列表"
                ]
            }
        }
    },
    "清体力_数构银本": {
        "recognition": {
            "param": {
                "expected": [
                    "前往"
                ]
            }
        }
    },
    "清体力_作战认证书": {
        "recognition": {
            "param": {
                "expected": [
                    "分析車廂"
                ]
            }
        }
    },
    "清体力_红本": {
        "recognition": {
            "param": {
                "expected": [
                    "前往"
                ]
            }
        }
    },
    "清体力_蓝本": {
        "recognition": {
            "param": {
                "expected": [
                    "前往"
                ]
            }
        }
    },
    "清体力_绿本": {
        "recognition": {
            "param": {
                "expected": [
                    "前往"
                ]
            }
        }
    },
    "清体力_黄本": {
        "recognition": {
            "param": {
                "expected": [
                    "前往"
                ]
            }
        }
    },
    "清体力_紫本": {
        "recognition": {
            "param": {
                "expected": [
                    "前往"
                ]
            }
        }
    },
    "清体力_强攻本": {
        "recognition": {
            "param": {
                "expected": [
                    "前往"
                ]
            }
        }
    },
    "清体力_特攻本": {
        "recognition": {
            "param": {
                "expected": [
                    "前往"
                ]
            }
        }
    },
    "清体力_突击本": {
        "recognition": {
            "param": {
                "expected": [
                    "前往"
                ]
            }
        }
    },
    "清体力_防护本": {
        "recognition": {
            "param": {
                "expected": [
                    "前往"
                ]
            }
        }
    },
    "清体力_辅助本": {
        "recognition": {
            "param": {
                "expected": [
                    "前往"
                ]
            }
        }
    },
    "清体力_演练卷": {
        "recognition": {
            "param": {
                "expected": [
                    "景觀車廂"
                ]
            }
        }
    },
    "清体力_整流器本": {
        "recognition": {
            "param": {
                "expected": [
                    "前往"
                ]
            }
        }
    },
    "清体力_卡带本": {
        "recognition": {
            "param": {
                "expected": [
                    "前往"
                ]
            }
        }
    },
    "清体力_选择卡带": {
        "recognition": {
            "param": {
                "expected": [
                    "查看詳情"
                ]
            }
        }
    },
    "清体力_冷酷者": {
        "recognition": {
            "param": {
                "expected": [
                    "冷酷者產線"
                ]
            }
        }
    },
    "清体力_确认卡带": {
        "recognition": {
            "param": {
                "expected": [
                    "確定"
                ]
            }
        }
    },
    "清体力_顿悟者": {
        "recognition": {
            "param": {
                "expected": [
                    "頓悟者產線"
                ]
            }
        }
    },
    "清体力_苦修者": {
        "recognition": {
            "param": {
                "expected": [
                    "苦修者產線"
                ]
            }
        }
    },
    "清体力_隐世者": {
        "recognition": {
            "param": {
                "expected": [
                    "隐世者產線"
                ]
            }
        }
    },
    "清体力_惊惧者": {
        "recognition": {
            "param": {
                "expected": [
                    "驚懼者產線"
                ]
            }
        }
    },
    "清体力_改造者": {
        "recognition": {
            "param": {
                "expected": [
                    "改造者产线"
                ]
            }
        }
    },
    "清体力_震荡者": {
        "recognition": {
            "param": {
                "expected": [
                    "震盪者產線"
                ]
            }
        }
    },
    "清体力_扭曲者": {
        "recognition": {
            "param": {
                "expected": [
                    "扭曲者產線"
                ]
            }
        }
    },
    "清体力_卡带": {
        "recognition": {
            "param": {
                "expected": [
                    "卡帶車廂"
                ]
            }
        }
    },
    "清体力_合约本": {
        "recognition": {
            "param": {
                "expected": [
                    "前往"
                ]
            }
        }
    },
    "清体力_苦味喷剂本": {
        "recognition": {
            "param": {
                "expected": [
                    "前往"
                ]
            }
        }
    },
    "清体力_存在将过期合剂": {
        "recognition": {
            "param": {
                "expected": [
                    "時"
                ]
            }
        }
    }
}